rigging/__init__.py
rigging/caching.py
rigging/chat.py
rigging/completion.py
rigging/data.py
rigging/error.py
rigging/generator/__init__.py
rigging/generator/__init__.pyi
rigging/generator/base.py
rigging/generator/http.py
rigging/generator/litellm_.py
rigging/generator/transformers_.py
rigging/generator/vllm_.py
rigging/interact.py
rigging/logging.py
rigging/message.py
rigging/model.py
rigging/parsing.py
rigging/prompt.py
rigging/py.typed
rigging/tokenizer/__init__.py
rigging/tokenizer/__init__.pyi
rigging/tokenizer/base.py
rigging/tokenizer/transformers_.py
rigging/tools/__init__.py
rigging/tools/base.py
rigging/tools/mcp.py
rigging/tools/robopages.py
rigging/transform/__init__.py
rigging/transform/base.py
rigging/transform/json_tools.py
rigging/transform/pythonic_tools.py
rigging/transform/xml_tools.py
rigging/util.py
rigging/version.py
rigging/watchers.py
rigging-3.3.5.dist-info/METADATA
rigging-3.3.5.dist-info/WHEEL
rigging-3.3.5.dist-info/licenses/LICENSE
rigging-3.3.5.dist-info/RECORD
