Metadata-Version: 2.4
Name: rigging
Version: 3.3.5
Summary: LLM Interaction Framework
License: MIT
License-File: LICENSE
Author: Nick Landers
Author-email: monoxgas@gmail.com
Requires-Python: >=3.10,<3.14
Classifier: License :: OSI Approved :: MIT License
Classifier: Programming Language :: Python :: 3
Classifier: Programming Language :: Python :: 3.10
Classifier: Programming Language :: Python :: 3.11
Classifier: Programming Language :: Python :: 3.12
Classifier: Programming Language :: Python :: 3.13
Provides-Extra: all
Provides-Extra: data
Provides-Extra: examples
Provides-Extra: llm
Requires-Dist: accelerate (>=0.30.1,<0.31.0) ; extra == "llm" or extra == "all"
Requires-Dist: aiodocker (>=0.22.2,<0.23.0) ; extra == "examples" or extra == "all"
Requires-Dist: asyncssh (>=2.14.2,<3.0.0) ; extra == "examples" or extra == "all"
Requires-Dist: click (>=8.1.7,<9.0.0) ; extra == "examples" or extra == "all"
Requires-Dist: colorama (>=0.4.6,<0.5.0)
Requires-Dist: dreadnode (>=1.12.0)
Requires-Dist: elasticsearch (>=8.13.2,<9.0.0) ; extra == "data" or extra == "all"
Requires-Dist: httpx (>=0.28.0,<0.29.0) ; extra == "examples" or extra == "all"
Requires-Dist: jsonpath-ng (>=1.7.0,<2.0.0)
Requires-Dist: jsonref (>=1.1.0,<2.0.0)
Requires-Dist: litellm (>=1.67.2,<2.0.0)
Requires-Dist: loguru (>=0.7.2,<0.8.0)
Requires-Dist: mcp (>=1.5.0,<2.0.0)
Requires-Dist: pandas (>=2.2.2,<3.0.0) ; extra == "data" or extra == "all"
Requires-Dist: pydantic (>=2.7.3,<3.0.0)
Requires-Dist: pydantic-xml (<=2.17.0)
Requires-Dist: ruamel-yaml (>=0.18.10,<0.19.0)
Requires-Dist: transformers (>=4.41.0,<5.0.0) ; extra == "llm" or extra == "all"
Requires-Dist: vllm (>=0.5.0,<0.6.0) ; extra == "llm" or extra == "all"
Requires-Dist: websockets (>=13.0,<14.0) ; extra == "examples" or extra == "all"
Requires-Dist: xmltodict (>=0.13.0,<0.14.0)
Project-URL: Repository, https://github.com/dreadnode/rigging
